{"data":{"allGhostSettings":{"edges":[{"node":{"title":"Gotsby Demo","description":"Thoughts, stories and ideas.","url":"https://cms.gotsby.org","logo":"https://static.gotsby.org/v1/assets/images/ghost-logo.svg","icon":null,"cover_image":"https://static.gotsby.org/v1/assets/images/publication-cover.png","facebook":"ghost","twitter":"@tryghost","lang":"en","timezone":"Etc/UTC","codeinjection_head":null,"codeinjection_foot":null,"codeinjection_styles":"","navigation":[{"label":"Home","url":"/"},{"label":"Tag","url":"/tag/getting-started/"},{"label":"Author","url":"/author/ghost/"},{"label":"Help","url":"https://www.jamify.org/"}],"secondary_navigation":[],"coverImageSharp":null}}]},"site":{"siteMetadata":{"siteUrl":"https://demo.jamify.org","postsPerPage":3,"siteTitleMeta":"Gatsby Starter Ghost CMS","siteDescriptionMeta":"Turn your Ghost blog into a flaring fast static site with Gatsby","shareImageWidth":1000,"shareImageHeight":523,"shortTitle":"Jamify","siteIcon":"favicon.png","backgroundColor":"#e9e9e9","themeColor":"#15171A","overwriteGhostNavigation":null,"navigation":null}}}}